{"opened": {"total_count": 40, "core": {"branches": {"develop": 27, "N/A": 7}, "internal": 12, "external": 22}, "repositories": {"ps_googleanalytics": {"total_count": 1, "internal": 0, "external": 1}, "ps_reminder": {"total_count": 1, "internal": 0, "external": 1}, "welcome": {"total_count": 2, "internal": 0, "external": 2}, "docker": {"total_count": 2, "internal": 2, "external": 0}}}, "closed": {"total_count": 47, "core": {"branches": {"develop": 36, "N/A": 2}, "internal": 12, "external": 26}, "repositories": {"welcome": {"total_count": 2, "internal": 0, "external": 2}, "docker": {"total_count": 3, "internal": 3, "external": 0}}}, "merged": {"total_count": 37, "core": {"branches": {"develop": 29, "N/A": 1}, "internal": 11, "external": 19}, "repositories": {"welcome": {"total_count": 2, "internal": 0, "external": 2}, "docker": {"total_count": 3, "internal": 3, "external": 0}}}}