{"opened": {"total_count": 70, "branches": {"N/A": 1}, "repositories": {"chronopost": 1, "bankwire": 1, "prestashop-ui-kit": 1, "cheque": 1, "homeslider": 2, "community-theme-16": 2, "oneandonehosting": 1, "blocknewsletter": 1, "blocklayered": 1, "dashproducts": 1, "blockcontact": 1, "amzpayments": 1}}, "closed": {"total_count": 84, "branches": {}, "repositories": {"bankwire": 1, "homeslider": 1, "community-theme-16": 2, "blocklayered": 1, "blockcontact": 1, "prestashop-ui-kit": 1, "blockcart": 1, "ebay": 1, "dpdfrance": 1, "avalaratax": 1, "simplifycommerce": 1, "hipay": 1}}, "merged": {"total_count": 60, "branches": {}, "repositories": {"bankwire": 1, "homeslider": 1, "community-theme-16": 2, "blocklayered": 1, "blockcontact": 1, "prestashop-ui-kit": 1, "blockcart": 1, "ebay": 1, "dpdfrance": 1, "avalaratax": 1, "simplifycommerce": 1, "hipay": 1}}}