{"opened": {"total_count": 26, "branches": {"1.7.4.x": 8, "develop": 8, "N/A": 2}, "repositories": {"ps_facetedsearch": 1, "ps_googleanalytics": 1, "docs": 1, "ps_mbo": 2, "docker-internal-images": 1, "prestonbot": 1, "ps_checkpayment": 1}}, "closed": {"total_count": 33, "branches": {"develop": 14, "1.7.4.x": 6, "N/A": 2}, "repositories": {"ps_googleanalytics": 2, "ps_mbo": 1, "docker-internal-images": 2, "psgdpr": 1, "welcome": 1, "docs": 1, "contactform": 1, "gamification": 1, "ps_linklist": 1}}, "merged": {"total_count": 26, "branches": {"develop": 12, "1.7.4.x": 5, "N/A": 1}, "repositories": {"ps_googleanalytics": 1, "ps_mbo": 1, "docker-internal-images": 1, "psgdpr": 1, "welcome": 1, "contactform": 1, "gamification": 1, "ps_linklist": 1}}}